offsock/offsock.py
offsock-1.0.0.dist-info/LICENSE
offsock-1.0.0.dist-info/METADATA
offsock-1.0.0.dist-info/WHEEL
offsock-1.0.0.dist-info/entry_points.txt
offsock-1.0.0.dist-info/top_level.txt
offsock-1.0.0.dist-info/RECORD
