Metadata-Version: 2.1
Name: offsock
Version: 1.0.0
Summary: An image offset grid generator inspired by your favorite socks.
Home-page: https://github.com/deletescape/offsock
Author: Till Kottmann
Author-email: me@deletescape.ch
License: MIT
Keywords: image socks grid offset
Platform: UNKNOWN
Classifier: Programming Language :: Python :: 3
Classifier: License :: OSI Approved :: MIT License
Classifier: Operating System :: OS Independent
Requires-Dist: Pillow (>=5.2.0)
Requires-Dist: click (>=7.0)
